py_scriptor/__init__.py
py_scriptor/scriptorIDE.py
py_scriptor-0.1.4.dist-info/LICENSE
py_scriptor-0.1.4.dist-info/METADATA
py_scriptor-0.1.4.dist-info/WHEEL
py_scriptor-0.1.4.dist-info/top_level.txt
py_scriptor-0.1.4.dist-info/RECORD
