Metadata-Version: 2.2
Name: py-scriptor
Version: 0.1.4
Summary: Scriptor is a small Python library for defining and running simple rule-based scripts
Author-email: libmaster169 on github <PRIVATE@EMAIL.COW>
License: MIT
Classifier: Programming Language :: Python :: 3
Classifier: License :: OSI Approved :: MIT License
Classifier: Operating System :: OS Independent
License-File: LICENSE
